pacmap/__init__.py
pacmap/pacmap.py
pacmap_dev-0.8.1rc3.dist-info/METADATA
pacmap_dev-0.8.1rc3.dist-info/WHEEL
pacmap_dev-0.8.1rc3.dist-info/licenses/LICENSE
pacmap_dev-0.8.1rc3.dist-info/RECORD
