Metadata-Version: 2.4
Name: pacmap-dev
Version: 0.8.1rc3
Summary: The UNOFFICIAL community implementation for PaCMAP: Pairwise Controlled Manifold Approximation Projection
Project-URL: Homepage, https://github.com/YingfanWang/PaCMAP
Project-URL: Bug Tracker, https://github.com/YingfanWang/PaCMAP/issues
Author: Haiyang Huang, Cynthia Rudin, Yaron Shaposhnik
Author-email: Yingfan Wang <yingfan.wang@duke.edu>
License-File: LICENSE
Classifier: Intended Audience :: Developers
Classifier: Intended Audience :: Science/Research
Classifier: License :: OSI Approved :: Apache Software License
Classifier: License :: OSI Approved :: MIT License
Classifier: Operating System :: OS Independent
Classifier: Programming Language :: Python :: 3
Requires-Python: >=3.8
Requires-Dist: annoy-mm>=1.17.3
Requires-Dist: numba>=0.57
Requires-Dist: numpy>=1.20
Requires-Dist: scikit-learn>=0.20
